CHANGES.txt
COPYRIGHT.txt
LICENSE.txt
README.txt
bootstrap.py
buildout.cfg
setup.py
z3c/__init__.py
z3c.suds.egg-info/PKG-INFO
z3c.suds.egg-info/SOURCES.txt
z3c.suds.egg-info/dependency_links.txt
z3c.suds.egg-info/namespace_packages.txt
z3c.suds.egg-info/requires.txt
z3c.suds.egg-info/top_level.txt
z3c.suds.egg-info/zip-safe
z3c/suds/__init__.py
z3c/suds/test.wsdl
z3c/suds/tests.py