Metadata-Version: 1.0
Name: z3c.suds
Version: 1.0
Summary: Manages a pool of suds SOAP clients within the context of a Zope application
Home-page: http://svn.zope.org/z3c.suds/trunk
Author: David Glick, Groundwire
Author-email: davidglick@groundwire.org
License: ZPL 2.1
Keywords: suds soap zope zodb
Platform: UNKNOWN
Classifier: Framework :: Plone
Classifier: Programming Language :: Python
